.codacy.yml
.gitignore
.gitlab-ci.yml
.prospector.yml
CHANGELOG.rst
CONTRIBUTING.rst
LICENSE
Makefile
README.md
environment.yml
requirements.txt
run_test.py
setup.py
docs/Makefile
docs/make.bat
docs/build/doctrees/authors.doctree
docs/build/doctrees/changelog.doctree
docs/build/doctrees/contributing.doctree
docs/build/doctrees/environment.pickle
docs/build/doctrees/formats.doctree
docs/build/doctrees/index.doctree
docs/build/doctrees/methods.doctree
docs/build/doctrees/object.doctree
docs/build/doctrees/projections.doctree
docs/build/doctrees/readme.doctree
docs/build/html/.buildinfo
docs/build/html/authors.html
docs/build/html/changelog.html
docs/build/html/contributing.html
docs/build/html/formats.html
docs/build/html/genindex.html
docs/build/html/index.html
docs/build/html/methods.html
docs/build/html/object.html
docs/build/html/objects.inv
docs/build/html/projections.html
docs/build/html/py-modindex.html
docs/build/html/readme.html
docs/build/html/search.html
docs/build/html/searchindex.js
docs/build/html/_modules/index.html
docs/build/html/_modules/nes/create_nes.html
docs/build/html/_modules/nes/load_nes.html
docs/build/html/_modules/nes/methods/cell_measures.html
docs/build/html/_modules/nes/methods/horizontal_interpolation.html
docs/build/html/_modules/nes/methods/spatial_join.html
docs/build/html/_modules/nes/methods/vertical_interpolation.html
docs/build/html/_modules/nes/nc_projections/default_nes.html
docs/build/html/_modules/nes/nc_projections/latlon_nes.html
docs/build/html/_modules/nes/nc_projections/lcc_nes.html
docs/build/html/_modules/nes/nc_projections/mercator_nes.html
docs/build/html/_modules/nes/nc_projections/points_nes.html
docs/build/html/_modules/nes/nc_projections/points_nes_ghost.html
docs/build/html/_modules/nes/nc_projections/points_nes_providentia.html
docs/build/html/_modules/nes/nc_projections/rotated_nes.html
docs/build/html/_modules/nes/nc_projections/rotated_nested_nes.html
nes.egg-info/PKG-INFO
nes.egg-info/SOURCES.txt
nes.egg-info/dependency_links.txt
nes.egg-info/entry_points.txt
nes.egg-info/requires.txt
nes.egg-info/top_level.txt
